nepali_date_cli/__init__.py
nepali_date_cli/cli.py
nepali_date_cli-0.1.8.dist-info/licenses/LICENSE
nepali_date_cli-0.1.8.dist-info/METADATA
nepali_date_cli-0.1.8.dist-info/WHEEL
nepali_date_cli-0.1.8.dist-info/entry_points.txt
nepali_date_cli-0.1.8.dist-info/top_level.txt
nepali_date_cli-0.1.8.dist-info/RECORD
