Metadata-Version: 2.4
Name: nepali-date-cli
Version: 0.1.8
Summary: A command-line tool to display Nepali date in your terminal.
Home-page: https://github.com/itznishantthapa/nepdate
Author: Nishant Thapa
Author-email: itsnishantu@gmail.com
License: MIT
Keywords: nepali date cli terminal miti
Classifier: Programming Language :: Python :: 3
Classifier: Operating System :: OS Independent
Classifier: Topic :: Utilities
Classifier: Environment :: Console
Requires-Python: >=3.6
License-File: LICENSE
Requires-Dist: nepali-datetime
Dynamic: author
Dynamic: author-email
Dynamic: classifier
Dynamic: description
Dynamic: description-content-type
Dynamic: home-page
Dynamic: keywords
Dynamic: license
Dynamic: license-file
Dynamic: requires-dist
Dynamic: requires-python
Dynamic: summary
